rayconfig/__init__.py
rayconfig/core.py
rayconfig/param.py
rayconfig-0.0.2.dist-info/LICENSE
rayconfig-0.0.2.dist-info/METADATA
rayconfig-0.0.2.dist-info/WHEEL
rayconfig-0.0.2.dist-info/top_level.txt
rayconfig-0.0.2.dist-info/RECORD
